ttsvowelviz/__init__.py
ttsvowelviz/_core.py
ttsvowelviz/_synthesizer.py
ttsvowelviz/forced_aligner/__init__.py
ttsvowelviz/forced_aligner/_forced_aligner.py
ttsvowelviz/forced_aligner/_web_maus_basic_aligner.py
ttsvowelviz/formant_extractor/__init__.py
ttsvowelviz/formant_extractor/_formant_extractor.py
ttsvowelviz/formant_extractor/_praat_formant_extractor.py
ttsvowelviz/utils/__init__.py
ttsvowelviz/utils/_language.py
ttsvowelviz/utils/_logger.py
ttsvowelviz/utils/_segment.py
ttsvowelviz/utils/constants.py
ttsvowelviz/vowel_space/__init__.py
ttsvowelviz/vowel_space/_dynamic_vowel_space.py
ttsvowelviz/vowel_space/_static_vowel_space.py
ttsvowelviz/vowel_space/_vowel_space.py
ttsvowelviz-0.1.0.dist-info/licenses/LICENSE
ttsvowelviz-0.1.0.dist-info/METADATA
ttsvowelviz-0.1.0.dist-info/WHEEL
ttsvowelviz-0.1.0.dist-info/top_level.txt
ttsvowelviz-0.1.0.dist-info/RECORD
