Metadata-Version: 2.4
Name: ttsvowelviz
Version: 0.1.0
Summary: A tool for visualizing static and dynamic vowel spaces during text-to-speech model training
Author-email: Pasindu Udawatta <pasindu.ud@gmail.com>
License: Copyright (c) 2025 Pasindu Udawatta
Project-URL: Repository, https://github.com/pasindu-ud/ttsvowelviz/tree/pypi-v0.1.0
Project-URL: Bug Tracker, https://github.com/pasindu-ud/ttsvowelviz/issues
Keywords: text-to-speech,vowel space,visualization,evaluation,linguistics
Classifier: Development Status :: 5 - Production/Stable
Classifier: Intended Audience :: Developers
Classifier: Intended Audience :: Information Technology
Classifier: Intended Audience :: Science/Research
Classifier: License :: OSI Approved :: MIT License
Classifier: Operating System :: OS Independent
Classifier: Programming Language :: Python :: 3
Classifier: Programming Language :: Python :: 3 :: Only
Classifier: Programming Language :: Python :: 3.7
Classifier: Programming Language :: Python :: 3.8
Classifier: Programming Language :: Python :: 3.9
Classifier: Programming Language :: Python :: 3.10
Classifier: Programming Language :: Python :: 3.11
Classifier: Programming Language :: Python :: 3.12
Classifier: Topic :: Scientific/Engineering
Classifier: Topic :: Scientific/Engineering :: Artificial Intelligence
Classifier: Topic :: Scientific/Engineering :: Visualization
Requires-Python: <3.13.0,>=3.7.0
License-File: LICENSE
Requires-Dist: numpy>=1.19.0
Requires-Dist: pandas>=1.0.0
Requires-Dist: plotly>=4.5.0
Requires-Dist: praat-parselmouth>=0.4.0
Requires-Dist: scipy>=1.5.0
Requires-Dist: tgt==1.5
Dynamic: license-file
